usefuladbplus/README.MD
usefuladbplus/__init__.py
usefuladbplus/requirements.txt
usefuladbplus/thirdparty.json
usefuladbplus-0.11.dist-info/LICENSE.rst
usefuladbplus-0.11.dist-info/METADATA
usefuladbplus-0.11.dist-info/WHEEL
usefuladbplus-0.11.dist-info/top_level.txt
usefuladbplus-0.11.dist-info/RECORD
