Metadata-Version: 2.1
Name: usefuladbplus
Version: 0.11
Summary: Automation library for ADB / Android
Home-page: https://github.com/hansalemaos/usefuladbplus
Author: Johannes Fischer
Author-email: aulasparticularesdealemaosp@gmail.com
License: MIT
Keywords: adb,android,bots
Classifier: Development Status :: 4 - Beta
Classifier: Programming Language :: Python :: 3 :: Only
Classifier: Programming Language :: Python :: 3.10
Classifier: Topic :: Software Development :: Libraries :: Python Modules
Classifier: Topic :: Utilities
License-File: LICENSE.rst
Requires-Dist: a-cv-imwrite-imread-plus
Requires-Dist: a-pandas-ex-apply-ignore-exceptions
Requires-Dist: adbeventparser
Requires-Dist: adbnativeblitz
Requires-Dist: flatten-everything
Requires-Dist: geteventplayback
Requires-Dist: istruthy
Requires-Dist: numexpr
Requires-Dist: numpy
Requires-Dist: opencv-python
Requires-Dist: opencv-python-headless
Requires-Dist: pandas
Requires-Dist: touchtouch
Requires-Dist: usefuladb
